{
  "resourceType": "namespaces/privateEndpointConnections",
  "apiVersion": "2022-10-01-preview",
  "learnMore": {
    "url": "https://learn.microsoft.com/powershell/module/az.servicebus"
  },
  "commands": [
    {
      "name": "Get-AzServiceBusPrivateEndpointConnection",
      "description": "Gets a description for the specified Private Endpoint Connection.",
      "path": "/subscriptions/{subscriptionId}/resourceGroups/{resourceGroupName}/providers/Microsoft.ServiceBus/namespaces/{namespaceName}/privateEndpointConnections/{privateEndpointConnectionName}",
      "help": {
        "learnMore": {
          "url": "https://learn.microsoft.com/powershell/module/az.servicebus/get-azservicebusprivateendpointconnection"
        },
        "parameterSets": [
          {
            "parameters": [
              "-Name <String>",
              "-NamespaceName <String>",
              "-ResourceGroupName <String>",
              "[-SubscriptionId <String[]>]"
            ]
          }
        ]
      },
      "examples": [
        {
          "description": "Gets a description for the specified Private Endpoint Connection.",
          "parameters": [
            {
              "name": "-Name",
              "value": "[Path.privateEndpointConnectionName]"
            },
            {
              "name": "-NamespaceName",
              "value": "[Path.namespaceName]"
            },
            {
              "name": "-ResourceGroupName",
              "value": "[Path.resourceGroupName]"
            },
            {
              "name": "-SubscriptionId",
              "value": "[Path.subscriptionId]"
            }
          ]
        }
      ]
    },
    {
      "name": "Remove-AzServiceBusPrivateEndpointConnection",
      "description": "Deletes an existing Private Endpoint Connection.",
      "path": "/subscriptions/{subscriptionId}/resourceGroups/{resourceGroupName}/providers/Microsoft.ServiceBus/namespaces/{namespaceName}/privateEndpointConnections/{privateEndpointConnectionName}",
      "help": {
        "learnMore": {
          "url": "https://learn.microsoft.com/powershell/module/az.servicebus/remove-azservicebusprivateendpointconnection"
        },
        "parameterSets": [
          {
            "parameters": [
              "-Name <String>",
              "-NamespaceName <String>",
              "-ResourceGroupName <String>",
              "[-SubscriptionId <String>]"
            ]
          }
        ]
      },
      "examples": [
        {
          "description": "Deletes an existing Private Endpoint Connection.",
          "parameters": [
            {
              "name": "-Name",
              "value": "[Path.privateEndpointConnectionName]"
            },
            {
              "name": "-NamespaceName",
              "value": "[Path.namespaceName]"
            },
            {
              "name": "-ResourceGroupName",
              "value": "[Path.resourceGroupName]"
            },
            {
              "name": "-SubscriptionId",
              "value": "[Path.subscriptionId]"
            }
          ]
        }
      ]
    }
  ]
}
