<?xml version="1.0" encoding="utf-8"?>
<helpItems schema="maml">
<command:command xmlns:maml="http://schemas.microsoft.com/maml/2004/10" xmlns:command="http://schemas.microsoft.com/maml/dev/command/2004/10" xmlns:dev="http://schemas.microsoft.com/maml/dev/2004/10" xmlns:MSHelp="http://msdn.microsoft.com/mshelp">
<!--Generated by PS Cmdlet Help Editor-->
	<command:details>
		<command:name>Get-AzureRmStorageAccount</command:name>
		<maml:description>
			<maml:para>Get the properties of a Storage Account</maml:para>
		</maml:description>
		<maml:copyright>
			<maml:para />
		</maml:copyright>
		<command:verb>Get</command:verb>
		<command:noun>AzureRmStorageAccount</command:noun>
		<dev:version />
	</command:details>
	<maml:description>
		<maml:para>This cmdlet allows you to get the properties of a specified Storage Account or all Storage Accounts within a Resource Group or the subscription.</maml:para>
	</maml:description>
	<command:syntax>
		<command:syntaxItem>
			<maml:name>Get-AzureRmStorageAccount</maml:name>
			<command:parameter required="false" variableLength="false" globbing="false" pipelineInput="true (ByPropertyName)" position="0">
				<maml:name>ResourceGroupName</maml:name>
				<maml:description>
					<maml:para>Name of the Resource Group</maml:para>
				</maml:description>
				<command:parameterValue required="true" variableLength="false">String</command:parameterValue>
			</command:parameter>
			<command:parameter required="false" variableLength="false" globbing="false" pipelineInput="true (ByPropertyName)" position="1">
				<maml:name>Name</maml:name>
				<maml:description>
					<maml:para>Name of the Storage Account</maml:para>
				</maml:description>
				<command:parameterValue required="true" variableLength="false">String</command:parameterValue>
			</command:parameter>
			<command:parameter required="false" variableLength="false" globbing="false" pipelineInput="false" position="named">
				<maml:name>Profile</maml:name>
				<maml:description>
					<maml:para />
				</maml:description>
				<command:parameterValue required="true" variableLength="false">AzureProfile</command:parameterValue>
			</command:parameter>
		</command:syntaxItem>
	</command:syntax>
	<command:parameters>
		<command:parameter required="false" variableLength="false" globbing="false" pipelineInput="true (ByPropertyName)" position="0">
			<maml:name>ResourceGroupName</maml:name>
			<maml:description>
				<maml:para>Name of the Resource Group</maml:para>
			</maml:description>
			<command:parameterValue required="true" variableLength="false">String</command:parameterValue>
			<dev:type>
				<maml:name>String</maml:name>
				<maml:uri/>
			</dev:type>
			<dev:defaultValue></dev:defaultValue>
		</command:parameter>
		<command:parameter required="false" variableLength="false" globbing="false" pipelineInput="true (ByPropertyName)" position="1">
			<maml:name>Name</maml:name>
			<maml:description>
				<maml:para>Name of the Storage Account</maml:para>
			</maml:description>
			<command:parameterValue required="true" variableLength="false">String</command:parameterValue>
			<dev:type>
				<maml:name>String</maml:name>
				<maml:uri/>
			</dev:type>
			<dev:defaultValue></dev:defaultValue>
		</command:parameter>
		<command:parameter required="false" variableLength="false" globbing="false" pipelineInput="false" position="named">
			<maml:name>Profile</maml:name>
			<maml:description>
				<maml:para />
			</maml:description>
			<command:parameterValue required="true" variableLength="false">AzureProfile</command:parameterValue>
			<dev:type>
				<maml:name>AzureProfile</maml:name>
				<maml:uri/>
			</dev:type>
			<dev:defaultValue></dev:defaultValue>
		</command:parameter>
	</command:parameters>
	<command:inputTypes>
		<command:inputType>
			<dev:type>
				<maml:name></maml:name>
				<maml:uri></maml:uri>
				<maml:description/>
			</dev:type>
			<maml:description>
				<maml:para>
</maml:para>
			</maml:description>
		</command:inputType>
	</command:inputTypes>
	<command:returnValues>
		<command:returnValue>
			<dev:type>
				<maml:name></maml:name>
				<maml:uri></maml:uri>
				<maml:description/>
			</dev:type>
			<maml:description>
				<maml:para>
</maml:para>
			</maml:description>
		</command:returnValue>
	</command:returnValues>
	<command:terminatingErrors></command:terminatingErrors>
	<command:nonTerminatingErrors></command:nonTerminatingErrors>
	<maml:alertSet>
		<maml:title></maml:title>
		<maml:alert>
			<maml:para />
            <maml:para>Keywords: azure, azurerm, arm, resource, management, manager, storage, container, account</maml:para>
		</maml:alert>
	</maml:alertSet>
	<command:examples>
		<command:example>
			<maml:title>--------------------------  Get a specified storage account  --------------------------</maml:title>
			<maml:introduction>
				<maml:paragraph>PS C:\&gt;</maml:paragraph>
			</maml:introduction>
			<dev:code>PS C:\&gt; #Get one storage account
          Get-AzureRmStorageAccount -ResourceGroupName &quot;rg1&quot; -AccountName &quot;mystorageaccount&quot;</dev:code>
			<dev:remarks>
				<maml:para />
				<maml:para />
				<maml:para />
				<maml:para></maml:para>
			</dev:remarks>
			<command:commandLines>
				<command:commandLine>
					<command:commandText>
						<maml:para />
					</command:commandText>
				</command:commandLine>
			</command:commandLines>
		</command:example>
		<command:example>
			<maml:title>--------------------------  Get all Storage Accounts in a Resource Group  --------------------------</maml:title>
			<maml:introduction>
				<maml:paragraph>PS C:\&gt;</maml:paragraph>
			</maml:introduction>
			<dev:code>PS C:\&gt; # Get all Storage Accounts in a Resource Group
          Get-AzureRmStorageAccount -ResourceGroupName &quot;rg1&quot;</dev:code>
			<dev:remarks>
				<maml:para />
				<maml:para />
				<maml:para />
				<maml:para></maml:para>
			</dev:remarks>
			<command:commandLines>
				<command:commandLine>
					<command:commandText>
						<maml:para />
					</command:commandText>
				</command:commandLine>
			</command:commandLines>
		</command:example>
		<command:example>
			<maml:title>--------------------------  Get all Storage Accounts in the subscription  --------------------------</maml:title>
			<maml:introduction>
				<maml:paragraph>PS C:\&gt;</maml:paragraph>
			</maml:introduction>
			<dev:code>PS C:\&gt; # Get all Storage Accounts in the subscription
          Get-AzureRmStorageAccount</dev:code>
			<dev:remarks>
				<maml:para />
				<maml:para />
				<maml:para />
				<maml:para></maml:para>
			</dev:remarks>
			<command:commandLines>
				<command:commandLine>
					<command:commandText>
						<maml:para />
					</command:commandText>
				</command:commandLine>
			</command:commandLines>
		</command:example>
	</command:examples>
	<maml:relatedLinks>
	</maml:relatedLinks>
</command:command>
<command:command xmlns:maml="http://schemas.microsoft.com/maml/2004/10" xmlns:command="http://schemas.microsoft.com/maml/dev/command/2004/10" xmlns:dev="http://schemas.microsoft.com/maml/dev/2004/10" xmlns:MSHelp="http://msdn.microsoft.com/mshelp">
<!--Generated by PS Cmdlet Help Editor-->
	<command:details>
		<command:name>Get-AzureRmStorageAccountKey</command:name>
		<maml:description>
			<maml:para>Get the access keys for an Azure storage account</maml:para>
		</maml:description>
		<maml:copyright>
			<maml:para />
		</maml:copyright>
		<command:verb>Get</command:verb>
		<command:noun>AzureRmStorageAccountKey</command:noun>
		<dev:version />
	</command:details>
	<maml:description>
		<maml:para>This cmdlet allows you to get the access keys for an Azure storage account.</maml:para>
	</maml:description>
	<command:syntax>
		<command:syntaxItem>
			<maml:name>Get-AzureRmStorageAccountKey</maml:name>
			<command:parameter required="true" variableLength="false" globbing="false" pipelineInput="true (ByPropertyName)" position="0">
				<maml:name>ResourceGroupName</maml:name>
				<maml:description>
					<maml:para>Name of the Resource Group</maml:para>
				</maml:description>
				<command:parameterValue required="true" variableLength="false">String</command:parameterValue>
			</command:parameter>
			<command:parameter required="true" variableLength="false" globbing="false" pipelineInput="true (ByPropertyName)" position="1">
				<maml:name>Name</maml:name>
				<maml:description>
					<maml:para>Name of the Storage Account</maml:para>
				</maml:description>
				<command:parameterValue required="true" variableLength="false">String</command:parameterValue>
			</command:parameter>
			<command:parameter required="false" variableLength="false" globbing="false" pipelineInput="false" position="named">
				<maml:name>Profile</maml:name>
				<maml:description>
					<maml:para />
				</maml:description>
				<command:parameterValue required="true" variableLength="false">AzureProfile</command:parameterValue>
			</command:parameter>
		</command:syntaxItem>
	</command:syntax>
	<command:parameters>
		<command:parameter required="true" variableLength="false" globbing="false" pipelineInput="true (ByPropertyName)" position="0">
			<maml:name>ResourceGroupName</maml:name>
			<maml:description>
				<maml:para>Name of the Resource Group</maml:para>
			</maml:description>
			<command:parameterValue required="true" variableLength="false">String</command:parameterValue>
			<dev:type>
				<maml:name>String</maml:name>
				<maml:uri/>
			</dev:type>
			<dev:defaultValue></dev:defaultValue>
		</command:parameter>
		<command:parameter required="true" variableLength="false" globbing="false" pipelineInput="true (ByPropertyName)" position="1">
			<maml:name>Name</maml:name>
			<maml:description>
				<maml:para>Name of the Storage Account</maml:para>
			</maml:description>
			<command:parameterValue required="true" variableLength="false">String</command:parameterValue>
			<dev:type>
				<maml:name>String</maml:name>
				<maml:uri/>
			</dev:type>
			<dev:defaultValue></dev:defaultValue>
		</command:parameter>
		<command:parameter required="false" variableLength="false" globbing="false" pipelineInput="false" position="named">
			<maml:name>Profile</maml:name>
			<maml:description>
				<maml:para />
			</maml:description>
			<command:parameterValue required="true" variableLength="false">AzureProfile</command:parameterValue>
			<dev:type>
				<maml:name>AzureProfile</maml:name>
				<maml:uri/>
			</dev:type>
			<dev:defaultValue></dev:defaultValue>
		</command:parameter>
	</command:parameters>
	<command:inputTypes>
		<command:inputType>
			<dev:type>
				<maml:name></maml:name>
				<maml:uri></maml:uri>
				<maml:description/>
			</dev:type>
			<maml:description>
				<maml:para>
</maml:para>
			</maml:description>
		</command:inputType>
	</command:inputTypes>
	<command:returnValues>
		<command:returnValue>
			<dev:type>
				<maml:name></maml:name>
				<maml:uri></maml:uri>
				<maml:description/>
			</dev:type>
			<maml:description>
				<maml:para>
</maml:para>
			</maml:description>
		</command:returnValue>
	</command:returnValues>
	<command:terminatingErrors></command:terminatingErrors>
	<command:nonTerminatingErrors></command:nonTerminatingErrors>
	<maml:alertSet>
		<maml:title></maml:title>
		<maml:alert>
			<maml:para />
            <maml:para>Keywords: azure, azurerm, arm, resource, management, manager, storage, container, account</maml:para>
		</maml:alert>
	</maml:alertSet>
	<command:examples>
		<command:example>
			<maml:title>--------------------------  Get the access keys for a Storage Account  --------------------------</maml:title>
			<maml:introduction>
				<maml:paragraph>PS C:\&gt;</maml:paragraph>
			</maml:introduction>
			<dev:code>#Get keys
          Get-AzureRmStorageAccountKey -ResourceGroupName &quot;rg1&quot; -AccountName &quot;mystorageaccount&quot;</dev:code>
			<dev:remarks>
				<maml:para />
				<maml:para />
				<maml:para />
				<maml:para></maml:para>
			</dev:remarks>
			<command:commandLines>
				<command:commandLine>
					<command:commandText>
						<maml:para />
					</command:commandText>
				</command:commandLine>
			</command:commandLines>
		</command:example>
	</command:examples>
	<maml:relatedLinks>
	</maml:relatedLinks>
</command:command>
<command:command xmlns:maml="http://schemas.microsoft.com/maml/2004/10" xmlns:command="http://schemas.microsoft.com/maml/dev/command/2004/10" xmlns:dev="http://schemas.microsoft.com/maml/dev/2004/10" xmlns:MSHelp="http://msdn.microsoft.com/mshelp">
<!--Generated by PS Cmdlet Help Editor-->
	<command:details>
		<command:name>Get-AzureRmStorageAccountNameAvailability</command:name>
		<maml:description>
			<maml:para>Check the availability of a storage account name.</maml:para>
		</maml:description>
		<maml:copyright>
			<maml:para />
		</maml:copyright>
		<command:verb>Get</command:verb>
		<command:noun>AzureRmStorageAccountNameAvailability</command:noun>
		<dev:version />
	</command:details>
	<maml:description>
		<maml:para>This cmdlet allows you to check whether the specified storage account name is valid or available to use.</maml:para>
	</maml:description>
	<command:syntax>
		<command:syntaxItem>
			<maml:name>Get-AzureRmStorageAccountNameAvailability</maml:name>
			<command:parameter required="true" variableLength="false" globbing="false" pipelineInput="true (ByPropertyName)" position="1">
				<maml:name>Name</maml:name>
				<maml:description>
					<maml:para>Storage account name to be checked.</maml:para>
				</maml:description>
				<command:parameterValue required="true" variableLength="false">String</command:parameterValue>
			</command:parameter>
			<command:parameter required="false" variableLength="false" globbing="false" pipelineInput="false" position="named">
				<maml:name>InformationAction</maml:name>
				<maml:description>
					<maml:para />
				</maml:description>
				<command:parameterValue required="true" variableLength="false">ActionPreference</command:parameterValue>
			</command:parameter>
			<command:parameter required="false" variableLength="false" globbing="false" pipelineInput="false" position="named">
				<maml:name>InformationVariable</maml:name>
				<maml:description>
					<maml:para />
				</maml:description>
				<command:parameterValue required="true" variableLength="false">String</command:parameterValue>
			</command:parameter>
		</command:syntaxItem>
	</command:syntax>
	<command:parameters>
		<command:parameter required="true" variableLength="false" globbing="false" pipelineInput="true (ByPropertyName)" position="1">
			<maml:name>Name</maml:name>
			<maml:description>
				<maml:para>Storage account name to be checked.</maml:para>
			</maml:description>
			<command:parameterValue required="true" variableLength="false">String</command:parameterValue>
			<dev:type>
				<maml:name>String</maml:name>
				<maml:uri/>
			</dev:type>
			<dev:defaultValue></dev:defaultValue>
		</command:parameter>
		<command:parameter required="false" variableLength="false" globbing="false" pipelineInput="false" position="named">
			<maml:name>InformationAction</maml:name>
			<maml:description>
				<maml:para />
			</maml:description>
			<command:parameterValue required="true" variableLength="false">ActionPreference</command:parameterValue>
			<dev:type>
				<maml:name>ActionPreference</maml:name>
				<maml:uri/>
			</dev:type>
			<dev:defaultValue></dev:defaultValue>
		</command:parameter>
		<command:parameter required="false" variableLength="false" globbing="false" pipelineInput="false" position="named">
			<maml:name>InformationVariable</maml:name>
			<maml:description>
				<maml:para />
			</maml:description>
			<command:parameterValue required="true" variableLength="false">String</command:parameterValue>
			<dev:type>
				<maml:name>String</maml:name>
				<maml:uri/>
			</dev:type>
			<dev:defaultValue></dev:defaultValue>
		</command:parameter>
	</command:parameters>
	<command:inputTypes>
		<command:inputType>
			<dev:type>
				<maml:name></maml:name>
				<maml:uri></maml:uri>
				<maml:description/>
			</dev:type>
			<maml:description>
<maml:para />
			</maml:description>
		</command:inputType>
	</command:inputTypes>
	<command:returnValues>
		<command:returnValue>
			<dev:type>
				<maml:name></maml:name>
				<maml:uri></maml:uri>
				<maml:description/>
			</dev:type>
			<maml:description>
<maml:para />
			</maml:description>
		</command:returnValue>
	</command:returnValues>
	<command:terminatingErrors></command:terminatingErrors>
	<command:nonTerminatingErrors></command:nonTerminatingErrors>
	<maml:alertSet>
		<maml:title></maml:title>
		<maml:alert>
			<maml:para />
		</maml:alert>
	</maml:alertSet>
	<command:examples>
		<command:example>
			<maml:title>--------------------------  Check availability of a storage account name  --------------------------</maml:title>
			<maml:introduction>
				<maml:paragraph>PS C:\&gt;</maml:paragraph>
			</maml:introduction>
			<dev:code>PS C:\&gt; Get-AzureRmStorageAccountNameAvailability -Name &quot;myaccountname&quot;</dev:code>
			<dev:remarks>
				<maml:para />
				<maml:para />
				<maml:para />
				<maml:para></maml:para>
			</dev:remarks>
			<command:commandLines>
				<command:commandLine>
					<command:commandText>
						<maml:para />
					</command:commandText>
				</command:commandLine>
			</command:commandLines>
		</command:example>
	</command:examples>
	<maml:relatedLinks>
	</maml:relatedLinks>
</command:command>
<command:command xmlns:maml="http://schemas.microsoft.com/maml/2004/10" xmlns:command="http://schemas.microsoft.com/maml/dev/command/2004/10" xmlns:dev="http://schemas.microsoft.com/maml/dev/2004/10" xmlns:MSHelp="http://msdn.microsoft.com/mshelp">
<!--Generated by PS Cmdlet Help Editor-->
	<command:details>
		<command:name>Get-AzureRmStorageUsage</command:name>
		<maml:description>
			<maml:para>Get the storage resource usage of current subscription.</maml:para>
		</maml:description>
		<maml:copyright>
			<maml:para />
		</maml:copyright>
		<command:verb>Get</command:verb>
		<command:noun>AzureRmStorageUsage</command:noun>
		<dev:version />
	</command:details>
	<maml:description>
		<maml:para>This cmdlet allows you to get the storage resource usage of current subscription.</maml:para>
	</maml:description>
	<command:syntax>
		<command:syntaxItem>
			<maml:name>Get-AzureRmStorageUsage</maml:name>
			<command:parameter required="false" variableLength="false" globbing="false" pipelineInput="false" position="named">
				<maml:name>InformationAction</maml:name>
				<maml:description>
					<maml:para />
				</maml:description>
				<command:parameterValue required="true" variableLength="false">ActionPreference</command:parameterValue>
			</command:parameter>
			<command:parameter required="false" variableLength="false" globbing="false" pipelineInput="false" position="named">
				<maml:name>InformationVariable</maml:name>
				<maml:description>
					<maml:para />
				</maml:description>
				<command:parameterValue required="true" variableLength="false">String</command:parameterValue>
			</command:parameter>
		</command:syntaxItem>
	</command:syntax>
	<command:parameters>
		<command:parameter required="false" variableLength="false" globbing="false" pipelineInput="false" position="named">
			<maml:name>InformationAction</maml:name>
			<maml:description>
				<maml:para />
			</maml:description>
			<command:parameterValue required="true" variableLength="false">ActionPreference</command:parameterValue>
			<dev:type>
				<maml:name>ActionPreference</maml:name>
				<maml:uri/>
			</dev:type>
			<dev:defaultValue></dev:defaultValue>
		</command:parameter>
		<command:parameter required="false" variableLength="false" globbing="false" pipelineInput="false" position="named">
			<maml:name>InformationVariable</maml:name>
			<maml:description>
				<maml:para />
			</maml:description>
			<command:parameterValue required="true" variableLength="false">String</command:parameterValue>
			<dev:type>
				<maml:name>String</maml:name>
				<maml:uri/>
			</dev:type>
			<dev:defaultValue></dev:defaultValue>
		</command:parameter>
	</command:parameters>
	<command:inputTypes>
		<command:inputType>
			<dev:type>
				<maml:name></maml:name>
				<maml:uri></maml:uri>
				<maml:description/>
			</dev:type>
			<maml:description>
<maml:para />
			</maml:description>
		</command:inputType>
	</command:inputTypes>
	<command:returnValues>
		<command:returnValue>
			<dev:type>
				<maml:name></maml:name>
				<maml:uri></maml:uri>
				<maml:description/>
			</dev:type>
			<maml:description>
<maml:para />
			</maml:description>
		</command:returnValue>
	</command:returnValues>
	<command:terminatingErrors></command:terminatingErrors>
	<command:nonTerminatingErrors></command:nonTerminatingErrors>
	<maml:alertSet>
		<maml:title></maml:title>
		<maml:alert>
			<maml:para />
		</maml:alert>
	</maml:alertSet>
	<command:examples>
		<command:example>
			<maml:title>--------------------------  Get the storage resources usage of current subscription  --------------------------</maml:title>
			<maml:introduction>
				<maml:paragraph>PS C:\&gt;</maml:paragraph>
			</maml:introduction>
			<dev:code></dev:code>
			<dev:remarks>
				<maml:para />
				<maml:para />
				<maml:para />
				<maml:para></maml:para>
			</dev:remarks>
			<command:commandLines>
				<command:commandLine>
					<command:commandText>
						<maml:para />
					</command:commandText>
				</command:commandLine>
			</command:commandLines>
		</command:example>
	</command:examples>
	<maml:relatedLinks>
	</maml:relatedLinks>
</command:command>
<command:command xmlns:maml="http://schemas.microsoft.com/maml/2004/10" xmlns:command="http://schemas.microsoft.com/maml/dev/command/2004/10" xmlns:dev="http://schemas.microsoft.com/maml/dev/2004/10" xmlns:MSHelp="http://msdn.microsoft.com/mshelp">
<!--Generated by PS Cmdlet Help Editor-->
	<command:details>
		<command:name>New-AzureRmStorageAccount</command:name>
		<maml:description>
			<maml:para>Allows you to create a new Storage Account</maml:para>
		</maml:description>
		<maml:copyright>
			<maml:para />
		</maml:copyright>
		<command:verb>New</command:verb>
		<command:noun>AzureRmStorageAccount</command:noun>
		<dev:version />
	</command:details>
	<maml:description>
		<maml:para>This cmdlet allows you to create a new Storage Account.</maml:para>
	</maml:description>
	<command:syntax>
		<command:syntaxItem>
			<maml:name>New-AzureRmStorageAccount</maml:name>
			<command:parameter required="true" variableLength="false" globbing="false" pipelineInput="true (ByPropertyName)" position="0">
				<maml:name>ResourceGroupName</maml:name>
				<maml:description>
					<maml:para>Name of the Resource Group</maml:para>
				</maml:description>
				<command:parameterValue required="true" variableLength="false">String</command:parameterValue>
			</command:parameter>
			<command:parameter required="true" variableLength="false" globbing="false" pipelineInput="true (ByPropertyName)" position="1">
				<maml:name>Name</maml:name>
				<maml:description>
					<maml:para>Name of the Storage Account</maml:para>
				</maml:description>
				<command:parameterValue required="true" variableLength="false">String</command:parameterValue>
			</command:parameter>
			<command:parameter required="true" variableLength="false" globbing="false" pipelineInput="true (ByPropertyName)" position="2">
				<maml:name>Type</maml:name>
				<maml:description>
					<maml:para>Type of Storage Account. Valid values are
• Standard_LRS (Locally-redundant storage)
• Standard_ZRS (Zone-redundant storage)
• Standard_GRS (Geo-redundant storage)
• Standard_RAGRS (Read access geo-redundant storage)</maml:para>
				</maml:description>
				<command:parameterValue required="true" variableLength="false">String</command:parameterValue>
			</command:parameter>
			<command:parameter required="true" variableLength="false" globbing="false" pipelineInput="true (ByPropertyName)" position="3">
				<maml:name>Location</maml:name>
				<maml:description>
					<maml:para>Location of the Storage Account</maml:para>
				</maml:description>
				<command:parameterValue required="true" variableLength="false">String</command:parameterValue>
			</command:parameter>
			<command:parameter required="false" variableLength="true" globbing="false" pipelineInput="true (ByPropertyName)" position="4">
				<maml:name>Tags</maml:name>
				<maml:description>
					<maml:para>Tags to set on the storage account.</maml:para>
				</maml:description>
				<command:parameterValue required="true" variableLength="true">Hashtable[]</command:parameterValue>
			</command:parameter>
			<command:parameter required="false" variableLength="false" globbing="false" pipelineInput="false" position="named">
				<maml:name>Profile</maml:name>
				<maml:description>
					<maml:para />
				</maml:description>
				<command:parameterValue required="true" variableLength="false">AzureProfile</command:parameterValue>
			</command:parameter>
		</command:syntaxItem>
	</command:syntax>
	<command:parameters>
		<command:parameter required="true" variableLength="false" globbing="false" pipelineInput="true (ByPropertyName)" position="0">
			<maml:name>ResourceGroupName</maml:name>
			<maml:description>
				<maml:para>Name of the Resource Group</maml:para>
			</maml:description>
			<command:parameterValue required="true" variableLength="false">String</command:parameterValue>
			<dev:type>
				<maml:name>String</maml:name>
				<maml:uri/>
			</dev:type>
			<dev:defaultValue></dev:defaultValue>
		</command:parameter>
		<command:parameter required="true" variableLength="false" globbing="false" pipelineInput="true (ByPropertyName)" position="1">
			<maml:name>Name</maml:name>
			<maml:description>
				<maml:para>Name of the Storage Account</maml:para>
			</maml:description>
			<command:parameterValue required="true" variableLength="false">String</command:parameterValue>
			<dev:type>
				<maml:name>String</maml:name>
				<maml:uri/>
			</dev:type>
			<dev:defaultValue></dev:defaultValue>
		</command:parameter>
		<command:parameter required="true" variableLength="false" globbing="false" pipelineInput="true (ByPropertyName)" position="2">
			<maml:name>Type</maml:name>
			<maml:description>
				<maml:para>Type of Storage Account. Valid values are
• Standard_LRS (Locally-redundant storage)
• Standard_ZRS (Zone-redundant storage)
• Standard_GRS (Geo-redundant storage)
• Standard_RAGRS (Read access geo-redundant storage)</maml:para>
			</maml:description>
			<command:parameterValue required="true" variableLength="false">String</command:parameterValue>
			<dev:type>
				<maml:name>String</maml:name>
				<maml:uri/>
			</dev:type>
			<dev:defaultValue></dev:defaultValue>
		</command:parameter>
		<command:parameter required="true" variableLength="false" globbing="false" pipelineInput="true (ByPropertyName)" position="3">
			<maml:name>Location</maml:name>
			<maml:description>
				<maml:para>Location of the Storage Account</maml:para>
			</maml:description>
			<command:parameterValue required="true" variableLength="false">String</command:parameterValue>
			<dev:type>
				<maml:name>String</maml:name>
				<maml:uri/>
			</dev:type>
			<dev:defaultValue></dev:defaultValue>
		</command:parameter>
		<command:parameter required="false" variableLength="true" globbing="false" pipelineInput="true (ByPropertyName)" position="4">
			<maml:name>Tags</maml:name>
			<maml:description>
				<maml:para>Tags to set on the storage account.</maml:para>
			</maml:description>
			<command:parameterValue required="true" variableLength="true">Hashtable[]</command:parameterValue>
			<dev:type>
				<maml:name>Hashtable[]</maml:name>
				<maml:uri/>
			</dev:type>
			<dev:defaultValue></dev:defaultValue>
		</command:parameter>
		<command:parameter required="false" variableLength="false" globbing="false" pipelineInput="false" position="named">
			<maml:name>Profile</maml:name>
			<maml:description>
				<maml:para />
			</maml:description>
			<command:parameterValue required="true" variableLength="false">AzureProfile</command:parameterValue>
			<dev:type>
				<maml:name>AzureProfile</maml:name>
				<maml:uri/>
			</dev:type>
			<dev:defaultValue></dev:defaultValue>
		</command:parameter>
	</command:parameters>
	<command:inputTypes>
		<command:inputType>
			<dev:type>
				<maml:name></maml:name>
				<maml:uri></maml:uri>
				<maml:description/>
			</dev:type>
			<maml:description>
				<maml:para>
</maml:para>
			</maml:description>
		</command:inputType>
	</command:inputTypes>
	<command:returnValues>
		<command:returnValue>
			<dev:type>
				<maml:name></maml:name>
				<maml:uri></maml:uri>
				<maml:description/>
			</dev:type>
			<maml:description>
				<maml:para>
</maml:para>
			</maml:description>
		</command:returnValue>
	</command:returnValues>
	<command:terminatingErrors></command:terminatingErrors>
	<command:nonTerminatingErrors></command:nonTerminatingErrors>
	<maml:alertSet>
		<maml:title></maml:title>
		<maml:alert>
			<maml:para />
            <maml:para>Keywords: azure, azurerm, arm, resource, management, manager, storage, container, account</maml:para>
		</maml:alert>
	</maml:alertSet>
	<command:examples>
		<command:example>
			<maml:title>--------------------------  Example 1  --------------------------</maml:title>
			<maml:introduction>
				<maml:paragraph>PS C:\&gt;</maml:paragraph>
			</maml:introduction>
			<dev:code>New-AzureRmStorageAccount -ResourceGroupName &quot;myresourcegroup&quot; -AccountName &quot;mystorageaccount&quot; -Location &quot;US West&quot; -Type &quot;Standard_GRS&quot;</dev:code>
			<dev:remarks>
				<maml:para />
				<maml:para />
				<maml:para />
				<maml:para></maml:para>
			</dev:remarks>
			<command:commandLines>
				<command:commandLine>
					<command:commandText>
						<maml:para />
					</command:commandText>
				</command:commandLine>
			</command:commandLines>
		</command:example>
	</command:examples>
	<maml:relatedLinks>
	</maml:relatedLinks>
</command:command>
<command:command xmlns:maml="http://schemas.microsoft.com/maml/2004/10" xmlns:command="http://schemas.microsoft.com/maml/dev/command/2004/10" xmlns:dev="http://schemas.microsoft.com/maml/dev/2004/10" xmlns:MSHelp="http://msdn.microsoft.com/mshelp">
<!--Generated by PS Cmdlet Help Editor-->
	<command:details>
		<command:name>New-AzureRmStorageAccountKey</command:name>
		<maml:description>
			<maml:para>Regenerates a storage key for an Azure storage account.</maml:para>
		</maml:description>
		<maml:copyright>
			<maml:para />
		</maml:copyright>
		<command:verb>New</command:verb>
		<command:noun>AzureRmStorageAccountKey</command:noun>
		<dev:version />
	</command:details>
	<maml:description>
		<maml:para>Regenerates a storage key for an Azure storage account.</maml:para>
	</maml:description>
	<command:syntax>
		<command:syntaxItem>
			<maml:name>New-AzureRmStorageAccountKey</maml:name>
			<command:parameter required="true" variableLength="false" globbing="false" pipelineInput="true (ByPropertyName)" position="0">
				<maml:name>ResourceGroupName</maml:name>
				<maml:description>
					<maml:para>Name of the Resource Group the storage account is in</maml:para>
				</maml:description>
				<command:parameterValue required="true" variableLength="false">String</command:parameterValue>
			</command:parameter>
			<command:parameter required="true" variableLength="false" globbing="false" pipelineInput="true (ByPropertyName)" position="1">
				<maml:name>Name</maml:name>
				<maml:description>
					<maml:para>Name of the Storage Account</maml:para>
				</maml:description>
				<command:parameterValue required="true" variableLength="false">String</command:parameterValue>
			</command:parameter>
			<command:parameter required="true" variableLength="false" globbing="false" pipelineInput="true (ByPropertyName)" position="2">
				<maml:name>KeyName</maml:name>
				<maml:description>
					<maml:para>Specifies which key to regenerate. Supported value set:
- “key1”
- “key2”</maml:para>
				</maml:description>
				<command:parameterValue required="true" variableLength="false">String</command:parameterValue>
			</command:parameter>
			<command:parameter required="false" variableLength="false" globbing="false" pipelineInput="false" position="named">
				<maml:name>Profile</maml:name>
				<maml:description>
					<maml:para />
				</maml:description>
				<command:parameterValue required="true" variableLength="false">AzureProfile</command:parameterValue>
			</command:parameter>
		</command:syntaxItem>
	</command:syntax>
	<command:parameters>
		<command:parameter required="true" variableLength="false" globbing="false" pipelineInput="true (ByPropertyName)" position="0">
			<maml:name>ResourceGroupName</maml:name>
			<maml:description>
				<maml:para>Name of the Resource Group the storage account is in</maml:para>
			</maml:description>
			<command:parameterValue required="true" variableLength="false">String</command:parameterValue>
			<dev:type>
				<maml:name>String</maml:name>
				<maml:uri/>
			</dev:type>
			<dev:defaultValue></dev:defaultValue>
		</command:parameter>
		<command:parameter required="true" variableLength="false" globbing="false" pipelineInput="true (ByPropertyName)" position="1">
			<maml:name>Name</maml:name>
			<maml:description>
				<maml:para>Name of the Storage Account</maml:para>
			</maml:description>
			<command:parameterValue required="true" variableLength="false">String</command:parameterValue>
			<dev:type>
				<maml:name>String</maml:name>
				<maml:uri/>
			</dev:type>
			<dev:defaultValue></dev:defaultValue>
		</command:parameter>
		<command:parameter required="true" variableLength="false" globbing="false" pipelineInput="true (ByPropertyName)" position="2">
			<maml:name>KeyName</maml:name>
			<maml:description>
				<maml:para>Specifies which key to regenerate. Supported value set:
- “key1”
- “key2”</maml:para>
			</maml:description>
			<command:parameterValue required="true" variableLength="false">String</command:parameterValue>
			<dev:type>
				<maml:name>String</maml:name>
				<maml:uri/>
			</dev:type>
			<dev:defaultValue></dev:defaultValue>
		</command:parameter>
		<command:parameter required="false" variableLength="false" globbing="false" pipelineInput="false" position="named">
			<maml:name>Profile</maml:name>
			<maml:description>
				<maml:para />
			</maml:description>
			<command:parameterValue required="true" variableLength="false">AzureProfile</command:parameterValue>
			<dev:type>
				<maml:name>AzureProfile</maml:name>
				<maml:uri/>
			</dev:type>
			<dev:defaultValue></dev:defaultValue>
		</command:parameter>
	</command:parameters>
	<command:inputTypes>
		<command:inputType>
			<dev:type>
				<maml:name></maml:name>
				<maml:uri></maml:uri>
				<maml:description/>
			</dev:type>
			<maml:description>
				<maml:para>
</maml:para>
			</maml:description>
		</command:inputType>
	</command:inputTypes>
	<command:returnValues>
		<command:returnValue>
			<dev:type>
				<maml:name></maml:name>
				<maml:uri></maml:uri>
				<maml:description/>
			</dev:type>
			<maml:description>
				<maml:para>
</maml:para>
			</maml:description>
		</command:returnValue>
	</command:returnValues>
	<command:terminatingErrors></command:terminatingErrors>
	<command:nonTerminatingErrors></command:nonTerminatingErrors>
	<maml:alertSet>
		<maml:title></maml:title>
		<maml:alert>
			<maml:para />
            <maml:para>Keywords: azure, azurerm, arm, resource, management, manager, storage, container, account</maml:para>
		</maml:alert>
	</maml:alertSet>
	<command:examples>
		<command:example>
			<maml:title>--------------------------  Example 1  --------------------------</maml:title>
			<maml:introduction>
				<maml:paragraph>PS C:\&gt;</maml:paragraph>
			</maml:introduction>
			<dev:code>#Regenerate a key
New-AzureRmStorageKey -ResourceGroupName &quot;myresourcegroup&quot; -AccountName &quot;mystorageaccount&quot; -keyName &quot;key1&quot;</dev:code>
			<dev:remarks>
				<maml:para />
				<maml:para />
				<maml:para />
				<maml:para></maml:para>
			</dev:remarks>
			<command:commandLines>
				<command:commandLine>
					<command:commandText>
						<maml:para />
					</command:commandText>
				</command:commandLine>
			</command:commandLines>
		</command:example>
	</command:examples>
	<maml:relatedLinks>
	</maml:relatedLinks>
</command:command>
<command:command xmlns:maml="http://schemas.microsoft.com/maml/2004/10" xmlns:command="http://schemas.microsoft.com/maml/dev/command/2004/10" xmlns:dev="http://schemas.microsoft.com/maml/dev/2004/10" xmlns:MSHelp="http://msdn.microsoft.com/mshelp">
<!--Generated by PS Cmdlet Help Editor-->
	<command:details>
		<command:name>Remove-AzureRmStorageAccount</command:name>
		<maml:description>
			<maml:para>Remove Storage Account from Azure</maml:para>
		</maml:description>
		<maml:copyright>
			<maml:para />
		</maml:copyright>
		<command:verb>Remove</command:verb>
		<command:noun>AzureRmStorageAccount</command:noun>
		<dev:version />
	</command:details>
	<maml:description>
		<maml:para>Remove Storage Account from Azure</maml:para>
	</maml:description>
	<command:syntax>
		<command:syntaxItem>
			<maml:name>Remove-AzureRmStorageAccount</maml:name>
			<command:parameter required="true" variableLength="false" globbing="false" pipelineInput="true (ByPropertyName)" position="0">
				<maml:name>ResourceGroupName</maml:name>
				<maml:description>
					<maml:para>Name of the Resource Group</maml:para>
				</maml:description>
				<command:parameterValue required="true" variableLength="false">String</command:parameterValue>
			</command:parameter>
			<command:parameter required="true" variableLength="false" globbing="false" pipelineInput="true (ByPropertyName)" position="1">
				<maml:name>Name</maml:name>
				<maml:description>
					<maml:para>Name of the VM</maml:para>
				</maml:description>
				<command:parameterValue required="true" variableLength="false">String</command:parameterValue>
			</command:parameter>
			<command:parameter required="false" variableLength="false" globbing="false" pipelineInput="false" position="named">
				<maml:name>Profile</maml:name>
				<maml:description>
					<maml:para />
				</maml:description>
				<command:parameterValue required="true" variableLength="false">AzureProfile</command:parameterValue>
			</command:parameter>
		</command:syntaxItem>
	</command:syntax>
	<command:parameters>
		<command:parameter required="true" variableLength="false" globbing="false" pipelineInput="true (ByPropertyName)" position="0">
			<maml:name>ResourceGroupName</maml:name>
			<maml:description>
				<maml:para>Name of the Resource Group</maml:para>
			</maml:description>
			<command:parameterValue required="true" variableLength="false">String</command:parameterValue>
			<dev:type>
				<maml:name>String</maml:name>
				<maml:uri/>
			</dev:type>
			<dev:defaultValue></dev:defaultValue>
		</command:parameter>
		<command:parameter required="true" variableLength="false" globbing="false" pipelineInput="true (ByPropertyName)" position="1">
			<maml:name>Name</maml:name>
			<maml:description>
				<maml:para>Name of the VM</maml:para>
			</maml:description>
			<command:parameterValue required="true" variableLength="false">String</command:parameterValue>
			<dev:type>
				<maml:name>String</maml:name>
				<maml:uri/>
			</dev:type>
			<dev:defaultValue></dev:defaultValue>
		</command:parameter>
		<command:parameter required="false" variableLength="false" globbing="false" pipelineInput="false" position="named">
			<maml:name>Profile</maml:name>
			<maml:description>
				<maml:para />
			</maml:description>
			<command:parameterValue required="true" variableLength="false">AzureProfile</command:parameterValue>
			<dev:type>
				<maml:name>AzureProfile</maml:name>
				<maml:uri/>
			</dev:type>
			<dev:defaultValue></dev:defaultValue>
		</command:parameter>
	</command:parameters>
	<command:inputTypes>
		<command:inputType>
			<dev:type>
				<maml:name></maml:name>
				<maml:uri></maml:uri>
				<maml:description/>
			</dev:type>
			<maml:description>
				<maml:para>
</maml:para>
			</maml:description>
		</command:inputType>
	</command:inputTypes>
	<command:returnValues>
		<command:returnValue>
			<dev:type>
				<maml:name></maml:name>
				<maml:uri></maml:uri>
				<maml:description/>
			</dev:type>
			<maml:description>
				<maml:para>
</maml:para>
			</maml:description>
		</command:returnValue>
	</command:returnValues>
	<command:terminatingErrors></command:terminatingErrors>
	<command:nonTerminatingErrors></command:nonTerminatingErrors>
	<maml:alertSet>
		<maml:title></maml:title>
		<maml:alert>
			<maml:para />
            <maml:para>Keywords: azure, azurerm, arm, resource, management, manager, storage, container, account</maml:para>
		</maml:alert>
	</maml:alertSet>
	<command:examples>
		<command:example>
			<maml:title>--------------------------  Remove Storage Account  --------------------------</maml:title>
			<maml:introduction>
				<maml:paragraph>PS C:\&gt;</maml:paragraph>
			</maml:introduction>
			<dev:code>PS C:\&gt; Remove-AzureRmStorageAccount -ResourceGroupName &quot;rg1&quot; -AccountName &quot;mystorageaccount&quot;</dev:code>
			<dev:remarks>
				<maml:para />
				<maml:para />
				<maml:para />
				<maml:para></maml:para>
			</dev:remarks>
			<command:commandLines>
				<command:commandLine>
					<command:commandText>
						<maml:para />
					</command:commandText>
				</command:commandLine>
			</command:commandLines>
		</command:example>
	</command:examples>
	<maml:relatedLinks>
	</maml:relatedLinks>
</command:command>
<command:command xmlns:maml="http://schemas.microsoft.com/maml/2004/10" xmlns:command="http://schemas.microsoft.com/maml/dev/command/2004/10" xmlns:dev="http://schemas.microsoft.com/maml/dev/2004/10" xmlns:MSHelp="http://msdn.microsoft.com/mshelp">
<!--Generated by PS Cmdlet Help Editor-->
	<command:details>
		<command:name>Set-AzureRmStorageAccount</command:name>
		<maml:description>
			<maml:para>Update the Storage Account properties</maml:para>
		</maml:description>
		<maml:copyright>
			<maml:para />
		</maml:copyright>
		<command:verb>Set</command:verb>
		<command:noun>AzureRmStorageAccount</command:noun>
		<dev:version />
	</command:details>
	<maml:description>
		<maml:para>This cmdlet allows you to update the Storage Account properties.</maml:para>
	</maml:description>
	<command:syntax>
		<command:syntaxItem>
			<maml:name>Set-AzureRmStorageAccount</maml:name>
			<command:parameter required="true" variableLength="false" globbing="false" pipelineInput="true (ByPropertyName)" position="0">
				<maml:name>ResourceGroupName</maml:name>
				<maml:description>
					<maml:para>Name of the Resource Group</maml:para>
				</maml:description>
				<command:parameterValue required="true" variableLength="false">String</command:parameterValue>
			</command:parameter>
			<command:parameter required="true" variableLength="false" globbing="false" pipelineInput="true (ByPropertyName)" position="1">
				<maml:name>Name</maml:name>
				<maml:description>
					<maml:para>Name of the Storage Account</maml:para>
				</maml:description>
				<command:parameterValue required="true" variableLength="false">String</command:parameterValue>
			</command:parameter>
			<command:parameter required="true" variableLength="false" globbing="false" pipelineInput="true (ByPropertyName)" position="2">
				<maml:name>Type</maml:name>
				<maml:description>
					<maml:para>Specifies the account type of the storage account. One of four options:
            • Standard_LRS (Locally-redundant storage)
            • Standard_GRS (Geo-redundant storage)
            • Standard_RAGRS (Read access geo-redundant storage)
            • Standard_ZRS

            Note that Standard_ZRS accounts cannot be changed to other account types, and other account types cannot be changed to Standard_ZRS.</maml:para>
				</maml:description>
				<command:parameterValue required="true" variableLength="false">String</command:parameterValue>
			</command:parameter>
			<command:parameter required="false" variableLength="false" globbing="false" pipelineInput="false" position="named">
				<maml:name>Profile</maml:name>
				<maml:description>
					<maml:para />
				</maml:description>
				<command:parameterValue required="true" variableLength="false">AzureProfile</command:parameterValue>
			</command:parameter>
		</command:syntaxItem>
		<command:syntaxItem>
			<maml:name>Set-AzureRmStorageAccount</maml:name>
			<command:parameter required="true" variableLength="false" globbing="false" pipelineInput="true (ByPropertyName)" position="0">
				<maml:name>ResourceGroupName</maml:name>
				<maml:description>
					<maml:para>Name of the Resource Group</maml:para>
				</maml:description>
				<command:parameterValue required="true" variableLength="false">String</command:parameterValue>
			</command:parameter>
			<command:parameter required="true" variableLength="false" globbing="false" pipelineInput="true (ByPropertyName)" position="1">
				<maml:name>Name</maml:name>
				<maml:description>
					<maml:para>Name of the Storage Account</maml:para>
				</maml:description>
				<command:parameterValue required="true" variableLength="false">String</command:parameterValue>
			</command:parameter>
			<command:parameter required="true" variableLength="false" globbing="false" pipelineInput="true (ByPropertyName)" position="2">
				<maml:name>CustomDomainName</maml:name>
				<maml:description>
					<maml:para>The name of the custom domain.</maml:para>
				</maml:description>
				<command:parameterValue required="true" variableLength="false">String</command:parameterValue>
			</command:parameter>
			<command:parameter required="false" variableLength="true" globbing="false" pipelineInput="true (ByPropertyName)" position="3">
				<maml:name>UseSubDomain</maml:name>
				<maml:description>
					<maml:para>Indicates whether indirect CName validation is enabled.</maml:para>
				</maml:description>
				<command:parameterValue required="true" variableLength="true">Nullable`1[Boolean]</command:parameterValue>
			</command:parameter>
			<command:parameter required="false" variableLength="false" globbing="false" pipelineInput="false" position="named">
				<maml:name>Profile</maml:name>
				<maml:description>
					<maml:para />
				</maml:description>
				<command:parameterValue required="true" variableLength="false">AzureProfile</command:parameterValue>
			</command:parameter>
		</command:syntaxItem>
		<command:syntaxItem>
			<maml:name>Set-AzureRmStorageAccount</maml:name>
			<command:parameter required="true" variableLength="false" globbing="false" pipelineInput="true (ByPropertyName)" position="0">
				<maml:name>ResourceGroupName</maml:name>
				<maml:description>
					<maml:para>Name of the Resource Group</maml:para>
				</maml:description>
				<command:parameterValue required="true" variableLength="false">String</command:parameterValue>
			</command:parameter>
			<command:parameter required="true" variableLength="false" globbing="false" pipelineInput="true (ByPropertyName)" position="1">
				<maml:name>Name</maml:name>
				<maml:description>
					<maml:para>Name of the Storage Account</maml:para>
				</maml:description>
				<command:parameterValue required="true" variableLength="false">String</command:parameterValue>
			</command:parameter>
			<command:parameter required="true" variableLength="true" globbing="false" pipelineInput="true (ByPropertyName)" position="2">
				<maml:name>Tags</maml:name>
				<maml:description>
					<maml:para>Tags to set on the storage account.</maml:para>
				</maml:description>
				<command:parameterValue required="true" variableLength="true">Hashtable[]</command:parameterValue>
			</command:parameter>
			<command:parameter required="false" variableLength="false" globbing="false" pipelineInput="false" position="named">
				<maml:name>Profile</maml:name>
				<maml:description>
					<maml:para />
				</maml:description>
				<command:parameterValue required="true" variableLength="false">AzureProfile</command:parameterValue>
			</command:parameter>
		</command:syntaxItem>
	</command:syntax>
	<command:parameters>
		<command:parameter required="true" variableLength="false" globbing="false" pipelineInput="true (ByPropertyName)" position="0">
			<maml:name>ResourceGroupName</maml:name>
			<maml:description>
				<maml:para>Name of the Resource Group</maml:para>
			</maml:description>
			<command:parameterValue required="true" variableLength="false">String</command:parameterValue>
			<dev:type>
				<maml:name>String</maml:name>
				<maml:uri/>
			</dev:type>
			<dev:defaultValue></dev:defaultValue>
		</command:parameter>
		<command:parameter required="true" variableLength="false" globbing="false" pipelineInput="true (ByPropertyName)" position="1">
			<maml:name>Name</maml:name>
			<maml:description>
				<maml:para>Name of the Storage Account</maml:para>
			</maml:description>
			<command:parameterValue required="true" variableLength="false">String</command:parameterValue>
			<dev:type>
				<maml:name>String</maml:name>
				<maml:uri/>
			</dev:type>
			<dev:defaultValue></dev:defaultValue>
		</command:parameter>
		<command:parameter required="true" variableLength="false" globbing="false" pipelineInput="true (ByPropertyName)" position="2">
			<maml:name>Type</maml:name>
			<maml:description>
				<maml:para>Specifies the account type of the storage account. One of four options:
            • Standard_LRS (Locally-redundant storage)
            • Standard_GRS (Geo-redundant storage)
            • Standard_RAGRS (Read access geo-redundant storage)
            • Standard_ZRS

            Note that Standard_ZRS accounts cannot be changed to other account types, and other account types cannot be changed to Standard_ZRS.</maml:para>
			</maml:description>
			<command:parameterValue required="true" variableLength="false">String</command:parameterValue>
			<dev:type>
				<maml:name>String</maml:name>
				<maml:uri/>
			</dev:type>
			<dev:defaultValue></dev:defaultValue>
		</command:parameter>
		<command:parameter required="false" variableLength="false" globbing="false" pipelineInput="false" position="named">
			<maml:name>Profile</maml:name>
			<maml:description>
				<maml:para />
			</maml:description>
			<command:parameterValue required="true" variableLength="false">AzureProfile</command:parameterValue>
			<dev:type>
				<maml:name>AzureProfile</maml:name>
				<maml:uri/>
			</dev:type>
			<dev:defaultValue></dev:defaultValue>
		</command:parameter>
		<command:parameter required="true" variableLength="false" globbing="false" pipelineInput="true (ByPropertyName)" position="2">
			<maml:name>CustomDomainName</maml:name>
			<maml:description>
				<maml:para>The name of the custom domain.</maml:para>
			</maml:description>
			<command:parameterValue required="true" variableLength="false">String</command:parameterValue>
			<dev:type>
				<maml:name>String</maml:name>
				<maml:uri/>
			</dev:type>
			<dev:defaultValue></dev:defaultValue>
		</command:parameter>
		<command:parameter required="false" variableLength="true" globbing="false" pipelineInput="true (ByPropertyName)" position="3">
			<maml:name>UseSubDomain</maml:name>
			<maml:description>
				<maml:para>Indicates whether indirect CName validation is enabled.</maml:para>
			</maml:description>
			<command:parameterValue required="true" variableLength="true">Nullable`1[Boolean]</command:parameterValue>
			<dev:type>
				<maml:name>Nullable`1[Boolean]</maml:name>
				<maml:uri/>
			</dev:type>
			<dev:defaultValue></dev:defaultValue>
		</command:parameter>
		<command:parameter required="true" variableLength="true" globbing="false" pipelineInput="true (ByPropertyName)" position="2">
			<maml:name>Tags</maml:name>
			<maml:description>
				<maml:para>Tags to set on the storage account.</maml:para>
			</maml:description>
			<command:parameterValue required="true" variableLength="true">Hashtable[]</command:parameterValue>
			<dev:type>
				<maml:name>Hashtable[]</maml:name>
				<maml:uri/>
			</dev:type>
			<dev:defaultValue></dev:defaultValue>
		</command:parameter>
	</command:parameters>
	<command:inputTypes>
		<command:inputType>
			<dev:type>
				<maml:name></maml:name>
				<maml:uri></maml:uri>
				<maml:description/>
			</dev:type>
			<maml:description>
				<maml:para>
</maml:para>
			</maml:description>
		</command:inputType>
	</command:inputTypes>
	<command:returnValues>
		<command:returnValue>
			<dev:type>
				<maml:name></maml:name>
				<maml:uri></maml:uri>
				<maml:description/>
			</dev:type>
			<maml:description>
				<maml:para>
</maml:para>
			</maml:description>
		</command:returnValue>
	</command:returnValues>
	<command:terminatingErrors></command:terminatingErrors>
	<command:nonTerminatingErrors></command:nonTerminatingErrors>
	<maml:alertSet>
		<maml:title></maml:title>
		<maml:alert>
			<maml:para />
            <maml:para>Keywords: azure, azurerm, arm, resource, management, manager, storage, container, account</maml:para>
		</maml:alert>
	</maml:alertSet>
	<command:examples>
		<command:example>
			<maml:title>--------------------------  Set Storage Account type  --------------------------</maml:title>
			<maml:introduction>
				<maml:paragraph>PS C:\&gt;</maml:paragraph>
			</maml:introduction>
			<dev:code>PS C:\&gt; # Set account type
          Set-AzureRmStorageAccount -ResourceGroupName &quot;myresourcegroup&quot; -AccountName &quot;mystorageaccount&quot; -Type &quot;Standard_RAGRS&quot;</dev:code>
			<dev:remarks>
				<maml:para />
				<maml:para />
				<maml:para />
				<maml:para></maml:para>
			</dev:remarks>
			<command:commandLines>
				<command:commandLine>
					<command:commandText>
						<maml:para />
					</command:commandText>
				</command:commandLine>
			</command:commandLines>
		</command:example>
		<command:example>
			<maml:title>--------------------------  Set Custom Domain  --------------------------</maml:title>
			<maml:introduction>
				<maml:paragraph>PS C:\&gt;</maml:paragraph>
			</maml:introduction>
			<dev:code>PS C:\&gt; #Set custom domain
          Set-AzureRmStorageAccount -ResourceGroupName &quot;myresourcegroup&quot; -AccountName &quot;mystorageaccount&quot; -CustomDomainName &quot;www.domainname.com&quot; –UseSubDomain $true</dev:code>
			<dev:remarks>
				<maml:para />
				<maml:para />
				<maml:para />
				<maml:para></maml:para>
			</dev:remarks>
			<command:commandLines>
				<command:commandLine>
					<command:commandText>
						<maml:para />
					</command:commandText>
				</command:commandLine>
			</command:commandLines>
		</command:example>
	</command:examples>
	<maml:relatedLinks>
	</maml:relatedLinks>
</command:command>
</helpItems>
