{
  "resourceType": "mobileNetworks",
  "apiVersion": "2022-11-01",
  "learnMore": {
    "url": "https://learn.microsoft.com/powershell/module/az.mobilenetwork"
  },
  "commands": [
    {
      "name": "Get-AzMobileNetwork",
      "description": "Gets information about the specified mobile network.",
      "path": "/subscriptions/{subscriptionId}/resourceGroups/{resourceGroupName}/providers/Microsoft.MobileNetwork/mobileNetworks/{mobileNetworkName}",
      "help": {
        "learnMore": {
          "url": "https://learn.microsoft.com/powershell/module/az.mobilenetwork/get-azmobilenetwork"
        },
        "parameterSets": [
          {
            "parameters": [
              "-Name <String>",
              "-ResourceGroupName <String>",
              "[-SubscriptionId <String[]>]"
            ]
          }
        ]
      },
      "examples": [
        {
          "description": "Gets information about the specified mobile network.",
          "parameters": [
            {
              "name": "-Name",
              "value": "[Path.mobileNetworkName]"
            },
            {
              "name": "-ResourceGroupName",
              "value": "[Path.resourceGroupName]"
            },
            {
              "name": "-SubscriptionId",
              "value": "[Path.subscriptionId]"
            }
          ]
        }
      ]
    },
    {
      "name": "Remove-AzMobileNetwork",
      "description": "Deletes the specified mobile network.",
      "path": "/subscriptions/{subscriptionId}/resourceGroups/{resourceGroupName}/providers/Microsoft.MobileNetwork/mobileNetworks/{mobileNetworkName}",
      "help": {
        "learnMore": {
          "url": "https://learn.microsoft.com/powershell/module/az.mobilenetwork/remove-azmobilenetwork"
        },
        "parameterSets": [
          {
            "parameters": [
              "-Name <String>",
              "-ResourceGroupName <String>",
              "[-SubscriptionId <String>]"
            ]
          }
        ]
      },
      "examples": [
        {
          "description": "Deletes the specified mobile network.",
          "parameters": [
            {
              "name": "-Name",
              "value": "[Path.mobileNetworkName]"
            },
            {
              "name": "-ResourceGroupName",
              "value": "[Path.resourceGroupName]"
            },
            {
              "name": "-SubscriptionId",
              "value": "[Path.subscriptionId]"
            }
          ]
        }
      ]
    }
  ]
}
