{
  "resourceType": "galleries/applications/versions",
  "apiVersion": "2022-01-03",
  "learnMore": {
    "url": "https://learn.microsoft.com/powershell/module/az.compute"
  },
  "commands": [
    {
      "name": "Get-AzGalleryApplicationVersion",
      "description": "Retrieves information about a gallery Application Version.",
      "path": "/subscriptions/{subscriptionId}/resourceGroups/{resourceGroupName}/providers/Microsoft.Compute/galleries/{galleryName}/applications/{galleryApplicationName}/versions/{galleryApplicationVersionName}",
      "help": {
        "learnMore": {
          "url": "https://learn.microsoft.com/powershell/module/az.compute/get-azgalleryapplicationversion"
        },
        "parameterSets": [
          {
            "parameters": [
              "-GalleryApplicationName <String>",
              "-GalleryName <String>",
              "-Name <String>",
              "-ResourceGroupName <String>",
              "[-SubscriptionId <String[]>]"
            ]
          }
        ]
      },
      "examples": [
        {
          "description": "Retrieves information about a gallery Application Version.",
          "parameters": [
            {
              "value": "[Path.galleryApplicationName]",
              "name": "-GalleryApplicationName"
            },
            {
              "value": "[Path.galleryName]",
              "name": "-GalleryName"
            },
            {
              "value": "[Path.galleryApplicationVersionName]",
              "name": "-Name"
            },
            {
              "value": "[Path.resourceGroupName]",
              "name": "-ResourceGroupName"
            },
            {
              "value": "[Path.subscriptionId]",
              "name": "-SubscriptionId"
            }
          ]
        }
      ]
    },
    {
      "name": "Remove-AzGalleryApplicationVersion",
      "description": "Delete a gallery Application Version.",
      "path": "/subscriptions/{subscriptionId}/resourceGroups/{resourceGroupName}/providers/Microsoft.Compute/galleries/{galleryName}/applications/{galleryApplicationName}/versions/{galleryApplicationVersionName}",
      "help": {
        "learnMore": {
          "url": "https://learn.microsoft.com/powershell/module/az.compute/remove-azgalleryapplicationversion"
        },
        "parameterSets": [
          {
            "parameters": [
              "-GalleryApplicationName <String>",
              "-GalleryName <String>",
              "-Name <String>",
              "-ResourceGroupName <String>",
              "[-SubscriptionId <String>]"
            ]
          }
        ]
      },
      "examples": [
        {
          "description": "Delete a gallery Application Version.",
          "parameters": [
            {
              "value": "[Path.galleryApplicationName]",
              "name": "-GalleryApplicationName"
            },
            {
              "value": "[Path.galleryName]",
              "name": "-GalleryName"
            },
            {
              "value": "[Path.galleryApplicationVersionName]",
              "name": "-Name"
            },
            {
              "value": "[Path.resourceGroupName]",
              "name": "-ResourceGroupName"
            },
            {
              "value": "[Path.subscriptionId]",
              "name": "-SubscriptionId"
            }
          ]
        }
      ]
    }
  ]
}
