{
  "resourceType": "organizations",
  "apiVersion": "2023-08-01",
  "learnMore": {
    "url": "https://learn.microsoft.com/powershell/module/az.astro"
  },
  "commands": [
    {
      "name": "Get-AzAstroOrganization",
      "description": "Get a OrganizationResource",
      "path": "/subscriptions/{subscriptionId}/resourceGroups/{resourceGroupName}/providers/Astronomer.Astro/organizations/{organizationName}",
      "help": {
        "learnMore": {
          "url": "https://learn.microsoft.com/powershell/module/az.astro/get-azastroorganization"
        },
        "parameterSets": [
          {
            "parameters": [
              "-Name <String>",
              "-ResourceGroupName <String>",
              "[-SubscriptionId <String[]>]"
            ]
          }
        ]
      },
      "examples": [
        {
          "description": "Get a OrganizationResource",
          "parameters": [
            {
              "name": "-Name",
              "value": "[Path.organizationName]"
            },
            {
              "name": "-ResourceGroupName",
              "value": "[Path.resourceGroupName]"
            },
            {
              "name": "-SubscriptionId",
              "value": "[Path.subscriptionId]"
            }
          ]
        }
      ]
    },
    {
      "name": "Remove-AzAstroOrganization",
      "description": "Delete a OrganizationResource",
      "path": "/subscriptions/{subscriptionId}/resourceGroups/{resourceGroupName}/providers/Astronomer.Astro/organizations/{organizationName}",
      "help": {
        "learnMore": {
          "url": "https://learn.microsoft.com/powershell/module/az.astro/remove-azastroorganization"
        },
        "parameterSets": [
          {
            "parameters": [
              "-Name <String>",
              "-ResourceGroupName <String>",
              "[-SubscriptionId <String>]"
            ]
          }
        ]
      },
      "examples": [
        {
          "description": "Delete a OrganizationResource",
          "parameters": [
            {
              "name": "-Name",
              "value": "[Path.organizationName]"
            },
            {
              "name": "-ResourceGroupName",
              "value": "[Path.resourceGroupName]"
            },
            {
              "name": "-SubscriptionId",
              "value": "[Path.subscriptionId]"
            }
          ]
        }
      ]
    }
  ]
}
